noauthsftp.py
noauthsftp-0.3.dist-info/DESCRIPTION.rst
noauthsftp-0.3.dist-info/METADATA
noauthsftp-0.3.dist-info/RECORD
noauthsftp-0.3.dist-info/WHEEL
noauthsftp-0.3.dist-info/entry_points.txt
noauthsftp-0.3.dist-info/metadata.json
noauthsftp-0.3.dist-info/top_level.txt
noauthsftp-0.3.dist-info/zip-safe
