Metadata-Version: 2.0
Name: noauthsftp
Version: 0.3
Summary: Simple SFTP server that allows all logins (anon sftp)
Home-page: http://blitz.works/noauthsftp
Author: Da_Blitz
Author-email: code@pocketnix.org
License: ISC
Keywords: ssh asyncio sftp server
Platform: UNKNOWN
Requires-Dist: asyncssh
Requires-Dist: distribute
